hltasr/__init__.py
hltasr/hltasr.py
hltasr-0.2.dist-info/METADATA
hltasr-0.2.dist-info/WHEEL
hltasr-0.2.dist-info/top_level.txt
hltasr-0.2.dist-info/RECORD
